odoo/addons/mrp_bom_attribute_match/README.rst
odoo/addons/mrp_bom_attribute_match/__init__.py
odoo/addons/mrp_bom_attribute_match/__manifest__.py
odoo/addons/mrp_bom_attribute_match/demo/product_product_demo.xml
odoo/addons/mrp_bom_attribute_match/i18n/es.po
odoo/addons/mrp_bom_attribute_match/i18n/hr.po
odoo/addons/mrp_bom_attribute_match/i18n/it.po
odoo/addons/mrp_bom_attribute_match/i18n/mrp_bom_attribute_match.pot
odoo/addons/mrp_bom_attribute_match/models/__init__.py
odoo/addons/mrp_bom_attribute_match/models/mrp_bom.py
odoo/addons/mrp_bom_attribute_match/models/mrp_production.py
odoo/addons/mrp_bom_attribute_match/models/product.py
odoo/addons/mrp_bom_attribute_match/readme/CONTRIBUTORS.rst
odoo/addons/mrp_bom_attribute_match/readme/DESCRIPTION.rst
odoo/addons/mrp_bom_attribute_match/readme/USAGE.rst
odoo/addons/mrp_bom_attribute_match/reports/__init__.py
odoo/addons/mrp_bom_attribute_match/reports/mrp_report_bom_structure.py
odoo/addons/mrp_bom_attribute_match/static/description/icon.png
odoo/addons/mrp_bom_attribute_match/static/description/index.html
odoo/addons/mrp_bom_attribute_match/tests/__init__.py
odoo/addons/mrp_bom_attribute_match/tests/common.py
odoo/addons/mrp_bom_attribute_match/tests/test_mrp_bom_attribute_match.py
odoo/addons/mrp_bom_attribute_match/tests/test_mrp_bom_attribute_match_nested.py
odoo/addons/mrp_bom_attribute_match/views/mrp_bom_views.xml
odoo14_addon_mrp_bom_attribute_match-14.0.1.2.6.dist-info/METADATA
odoo14_addon_mrp_bom_attribute_match-14.0.1.2.6.dist-info/WHEEL
odoo14_addon_mrp_bom_attribute_match-14.0.1.2.6.dist-info/top_level.txt
odoo14_addon_mrp_bom_attribute_match-14.0.1.2.6.dist-info/RECORD
